{
	"class" : {
		"newForRp" : "DataCurator 10/02/2012 14:30" },
	"instance" : {
		"_inspect" : "DataCurator 10/02/2012 14:30",
		"argNodes" : "DataCurator 10/02/2012 14:30",
		"irReceiverNode" : "DataCurator 10/02/2012 14:30",
		"isSmalltalkSend" : "DataCurator 10/02/2012 14:30",
		"name:" : "DataCurator 10/02/2012 14:30",
		"node_assign_set_rhs:" : "DataCurator 10/02/2012 14:30",
		"selector" : "DataCurator 10/02/2012 14:30",
		"valueNode:" : "DataCurator 10/02/2012 14:30",
		"walkWithScope:" : "DataCurator 10/02/2012 14:30" } }
